{"results": [{"comment": "Subscribe to our new English Global News Channel that is coming soon!!! \nWhat is VOGS Media??? - Know More - https://www.youtube.com/ \u2068@vogsmedia\u2069", "is_toxic": false, "lang": "en", "sentiment": "1", "timestamp": null, "toxicity_score": 0, "votes": 60}, {"comment": "Iran be like :- make America regrat again\ud83d\ude02\ud83d\ude02", "is_toxic": false, "lang": "id", "sentiment": "0", "timestamp": null, "toxicity_score": 0, "votes": 464}, {"comment": "Fatherland is frying\nMotherland is crying\nAndhbhakt is drying\nDeshbhakt is growing \ud83d\udd25\ud83e\ude77", "is_toxic": false, "lang": "en", "sentiment": "-1", "timestamp": null, "toxicity_score": 0, "votes": 282}, {"comment": "Iran has right to defend itself", "is_toxic": false, "lang": "en", "sentiment": "1", "timestamp": null, "toxicity_score": 0, "votes": 291}, {"comment": "Bought a gas cylinder for 3800 today.\nACHHEEEEE DINNNNN AAAA GYEEEEE", "is_toxic": false, "lang": "en", "sentiment": "0", "timestamp": null, "toxicity_score": 0, "votes": 218}, {"comment": "Main question is:- are people of usa that fool they chose this man as president??", "is_toxic": false, "lang": "en", "sentiment": "1", "timestamp": null, "toxicity_score": 0, "votes": 166}, {"comment": "Indian media \u274c\nThe Desh Bhakt media \u2705", "is_toxic": false, "lang": "id", "sentiment": "0", "timestamp": null, "toxicity_score": 0, "votes": 76}, {"comment": "Maths is not mathsing\ud83d\ude02\ud83d\ude02\ud83d\ude02", "is_toxic": false, "lang": "en", "sentiment": "0", "timestamp": null, "toxicity_score": 0, "votes": 9}, {"comment": "America in movies \ud83d\udc80\nAmerica in ground reality - she was a fairy \ud83e\uddda.", "is_toxic": false, "lang": "en", "sentiment": "0", "timestamp": null, "toxicity_score": 0, "votes": 82}, {"comment": "\"Trump ki diplomacy: Pehle bomb \ud83d\udca3 feko, phir pucho 'Dinner pe aaoge?'\"\ud83d\ude02", "is_toxic": false, "lang": "en", "sentiment": "0", "timestamp": null, "toxicity_score": 0, "votes": 36}, {"comment": "Indian Media \u274c \nThe Deshbhakt \u2705\nDhruv Rathee \u2705 \nRavish Kumar \u2705", "is_toxic": false, "lang": "en", "sentiment": "0", "timestamp": null, "toxicity_score": 0, "votes": 36}, {"comment": "Dear Akash please invite bhakt Banerjee, I wanted to know his opinion on Iran - Israel war and cylinder crisis.\ud83d\ude02\ud83d\ude02", "is_toxic": false, "lang": "en", "sentiment": "0", "timestamp": null, "toxicity_score": 0, "votes": 35}, {"comment": "\u092f\u0941\u0926\u094d\u0927 \u092e\u0947\u0902 \u0905\u092a\u0928\u0940 \u092c\u0939\u093e\u0926\u0941\u0930\u0940 \u0926\u093f\u0916\u093e\u0928\u0947 \u0935\u093e\u0932\u0947 \u0908\u0930\u093e\u0928\u093f\u092f\u094b\u0902 \u0915\u094b \u0932\u093e\u0916\u094b\u0902 \u0938\u0932\u093e\u092e\u0964", "is_toxic": false, "lang": "hi", "sentiment": "0", "timestamp": null, "toxicity_score": 0, "votes": 94}, {"comment": "Donald Trump the joker\u274c\nDonald duck the cartoon\u2611\ufe0f", "is_toxic": false, "lang": "en", "sentiment": "0", "timestamp": null, "toxicity_score": 0, "votes": 24}, {"comment": "America ka paw paw ho gayaa\ud83e\udd23\ud83d\ude02", "is_toxic": false, "lang": "tl", "sentiment": "0", "timestamp": null, "toxicity_score": 0, "votes": 105}, {"comment": "Iranian's do have balls of steel.", "is_toxic": false, "lang": "en", "sentiment": "0", "timestamp": null, "toxicity_score": 0, "votes": 28}, {"comment": "They all should be accountable for war criminals.", "is_toxic": false, "lang": "en", "sentiment": "0", "timestamp": null, "toxicity_score": 0, "votes": 25}, {"comment": "\u092d\u0915\u094d\u0924: \"Trump \u0915\u0947 \u091a\u0930\u0923\u094b\u0902 \u0915\u0947 \u0938\u093f\u0935\u093e \u092e\u0941\u091d\u0947 \u0915\u0941\u091b \u0928\u0939\u0940\u0902 \u0926\u093f\u0916 \u0930\u0939\u093e \u0930\u0947\u0964\"\n\ud83d\ude04\ud83d\ude04\ud83d\ude02", "is_toxic": false, "lang": "hi", "sentiment": "0", "timestamp": null, "toxicity_score": 0, "votes": 45}, {"comment": "Battle of bastards \ud83c\udfc7\ud83c\udffb\u274c battle of clowns \ud83e\udd21\u2705", "is_toxic": false, "lang": "en", "sentiment": "0", "timestamp": null, "toxicity_score": 0, "votes": 11}, {"comment": "Trump: I am done, but I don't know how to do it\ud83e\udd23\ud83e\udd23\ud83e\udd23", "is_toxic": false, "lang": "en", "sentiment": "0", "timestamp": null, "toxicity_score": 0, "votes": 19}, {"comment": "i  am waiting for you video", "is_toxic": false, "lang": "en", "sentiment": "0", "timestamp": null, "toxicity_score": 0, "votes": 2}, {"comment": "It\u2019s not circus \n\nUS doesn\u2019t care what happens there \n\nWhat world doesn\u2019t know is US is energy independent, they have reserves they don\u2019t use until it\u2019s needed. \n\nIf anything if infrastructure is destroyed \u2026 it will affect world \u2026 it\u2019s bad for everyone but point is it affects world more", "is_toxic": false, "lang": "en", "sentiment": "-1", "timestamp": null, "toxicity_score": 0, "votes": 1}, {"comment": "\u200b\u00a0@JpDigitalMedia\u00a0 yes Trump  itna bhi bewakoof nahi hai. \n\n\nPsychopathic narcissistic personality he is. Not easy to describe in simple words. \n\nHe cares about nothing but one's own self -- not even America and Americans. Its self centrism taken to its  extreme. \n\nHe is running this 'circus' to fling the crypto and blackmarkets and make money.", "is_toxic": false, "lang": "en", "sentiment": "-1", "timestamp": null, "toxicity_score": 0, "votes": 0}, {"comment": "war of fools", "is_toxic": false, "lang": "unknown", "sentiment": "0", "timestamp": null, "toxicity_score": 0, "votes": 1}, {"comment": "@thedeshbhakt\u00a0 https://youtu.be/kJQC01BgXMc?si=mv-z-2AEzJ481t92", "is_toxic": false, "lang": "en", "sentiment": "0", "timestamp": null, "toxicity_score": 0, "votes": 1}, {"comment": "Bhai AI Bubble burst pe video banao nah mereko doubt hain ki btech cse in ai will be bad if ai bubble burst because of this war", "is_toxic": false, "lang": "en", "sentiment": "-1", "timestamp": null, "toxicity_score": 0, "votes": 1}, {"comment": "Best of luck for VOGS Akash ji. Already did as much as I could now and subscribed. Will try my best to do more in the future once I am able to. Salute to your independent journalism.", "is_toxic": false, "lang": "en", "sentiment": "1", "timestamp": null, "toxicity_score": 0, "votes": 0}, {"comment": "You are the voice of India Sir \u2764", "is_toxic": false, "lang": "en", "sentiment": "0", "timestamp": null, "toxicity_score": 0, "votes": 0}, {"comment": "American hegemony will end soon", "is_toxic": false, "lang": "en", "sentiment": "0", "timestamp": null, "toxicity_score": 0, "votes": 0}, {"comment": "Best of luck for VOGS Akash !!", "is_toxic": false, "lang": "en", "sentiment": "1", "timestamp": null, "toxicity_score": 0, "votes": 0}, {"comment": "Link is not working", "is_toxic": false, "lang": "af", "sentiment": "0", "timestamp": null, "toxicity_score": 0, "votes": 0}, {"comment": "Sir Quba main kya ho raha hai \ud83e\udd28\ud83e\udd28\ud83e\udd28", "is_toxic": false, "lang": "so", "sentiment": "1", "timestamp": null, "toxicity_score": 0, "votes": 0}, {"comment": "NOPE/  TRUMP is escalating fight in background in media says war ends - but sent troops , same way iran can block hormuz yet heard that nato  person resigned claiming nuke action possibilities on oran as surprise / so  USA can not bear defaeat  BECAUSE  DEFEAT MEANSIN SIMPLY LOSING MONEY SOURCES UAE ETC. // and U R MISSING 1 IMP POINT WITH WAR USA ALSO GETTING BEENFIT / usa is also exporter of oil --- suprressing middle east  usa can sell their oil at 200$ // so war is thusa allowed eir earning mechanism (with or without war they are earning-- and no possibilites of end of war but there can be just  few days of halt for  money making  through share mkt via insider tradings)", "is_toxic": false, "lang": "en", "sentiment": "-1", "timestamp": null, "toxicity_score": 0, "votes": 0}, {"comment": "\ud83c\uddee\ud83c\uddf7\ud83c\uddf7\ud83c\uddfa\ud83c\udde8\ud83c\uddf3\ud83c\uddf0\ud83c\uddf5\niran.Russia.China.North Korea.\nGood Friendship.. \u2764\ufe0f", "is_toxic": false, "lang": "en", "sentiment": "1", "timestamp": null, "toxicity_score": 0, "votes": 0}, {"comment": "Regret ka spelling galat h bro.", "is_toxic": false, "lang": "sv", "sentiment": "0", "timestamp": null, "toxicity_score": 0, "votes": 9}, {"comment": "\u200b@dipshikha68hota hai bhai \ud83d\ude02\ud83d\ude02 Trump ka coffee ka spelling galat tha ban gaya na president \ud83d\ude02\ud83d\ude02", "is_toxic": false, "lang": "id", "sentiment": "0", "timestamp": null, "toxicity_score": 0, "votes": 7}, {"comment": "MARA", "is_toxic": false, "lang": "unknown", "sentiment": "0", "timestamp": null, "toxicity_score": 0, "votes": 7}, {"comment": "Regret*", "is_toxic": false, "lang": "unknown", "sentiment": "0", "timestamp": null, "toxicity_score": 0, "votes": 2}, {"comment": "nailed it", "is_toxic": false, "lang": "unknown", "sentiment": "0", "timestamp": null, "toxicity_score": 0, "votes": 1}, {"comment": "*regret", "is_toxic": false, "lang": "unknown", "sentiment": "0", "timestamp": null, "toxicity_score": 0, "votes": 1}, {"comment": "MARA??", "is_toxic": false, "lang": "unknown", "sentiment": "0", "timestamp": null, "toxicity_score": 0, "votes": 0}, {"comment": "\ud83d\ude02\ud83d\ude02\ud83d\ude02\ud83d\ude02\ud83d\ude02\ud83d\ude02", "is_toxic": false, "lang": "unknown", "sentiment": "0", "timestamp": null, "toxicity_score": 0, "votes": 0}, {"comment": "\ud83d\ude02\ud83d\ude02\ud83d\ude02Bhai uske bhavnao ko samzo Spelling Mistake gaya tel lene.\nTel ke picche to Trump pada hai\ud83d\ude02\ud83d\ude02\ud83d\ude02", "is_toxic": false, "lang": "id", "sentiment": "0", "timestamp": null, "toxicity_score": 0, "votes": 0}, {"comment": "regret likhna toh seekh bhai", "is_toxic": false, "lang": "sv", "sentiment": "0", "timestamp": null, "toxicity_score": 0, "votes": 0}, {"comment": "Zabardast bhai \ud83d\ude02\ud83d\ude02\ud83d\ude02\ud83d\ude02", "is_toxic": false, "lang": "id", "sentiment": "0", "timestamp": null, "toxicity_score": 0, "votes": 0}, {"comment": "\u0938\u0939\u0940 \u092a\u0915\u0921\u093c\u0947 \u0939\u0948 \ud83d\ude02", "is_toxic": false, "lang": "unknown", "sentiment": "0", "timestamp": null, "toxicity_score": 0, "votes": 5}, {"comment": "Fatherland ( arabia) Licking ass of trump\ud83e\udd70\ud83e\udd23\ud83e\udd23\ud83e\udd23", "is_toxic": false, "lang": "en", "sentiment": "0", "timestamp": null, "toxicity_score": 0, "votes": 5}, {"comment": "@Krishna-pp8wz\u00a0 Lol muslims also say the same thing for the heads of arab countries well i say u are right mbs is the biggest traitor in the world but still iran and other countries are going strong and muslims do help each other and are not divided through castes and stuff what they are doing is ethnic tension lol but i hope atleast u understand humanity and atleast understand that no innocent person should be killed whether they are hindu muslim chirstian jews etc", "is_toxic": false, "lang": "en", "sentiment": "1", "timestamp": null, "toxicity_score": 0, "votes": 2}, {"comment": "@Krishna-pp8wz\u00a0 i hope u understand that religious persecution existed in each and every religion no religion is great and none religion promoted it i hope u also pray for peace and dont enjoy the killings of other minority group cuz u just hate them i hope u also understand that no religion wants war", "is_toxic": false, "lang": "en", "sentiment": "1", "timestamp": null, "toxicity_score": 1, "votes": 0}, {"comment": "\ud83d\udc4d\ud83d\udc4d\ud83d\udc4d\ud83d\udc4d", "is_toxic": false, "lang": "unknown", "sentiment": "0", "timestamp": null, "toxicity_score": 0, "votes": 4}, {"comment": "Pakistani spotted", "is_toxic": false, "lang": "sl", "sentiment": "0", "timestamp": null, "toxicity_score": 0, "votes": 4}, {"comment": "https://youtu.be/dTsNdD5QPz4?si=qAz2drCv_RQKsv4J part 2\ud83c\udf89\ud83c\udf89", "is_toxic": false, "lang": "fr", "sentiment": "0", "timestamp": null, "toxicity_score": 0, "votes": 0}, {"comment": "bro if you have not watch full video then dont comment he was reffering jews community in india as their fatherland israel but other thing you written was good", "is_toxic": false, "lang": "en", "sentiment": "1", "timestamp": null, "toxicity_score": 0, "votes": 0}, {"comment": "Aabbu To Gaye \ud83d\ude05", "is_toxic": false, "lang": "so", "sentiment": "0", "timestamp": null, "toxicity_score": 0, "votes": 0}, {"comment": "Aag laga di aag laga di \ud83d\ude02\ud83d\ude02", "is_toxic": false, "lang": "so", "sentiment": "0", "timestamp": null, "toxicity_score": 0, "votes": 0}, {"comment": "\u2764\u2764", "is_toxic": false, "lang": "unknown", "sentiment": "0", "timestamp": null, "toxicity_score": 0, "votes": 0}, {"comment": "\ud83d\ude02 Pakistan bombed Afghanistan killed 400 muslims but sarrr ummah sarrrrr", "is_toxic": false, "lang": "id", "sentiment": "-1", "timestamp": null, "toxicity_score": 0, "votes": 4}, {"comment": "\u200b\u00a0@Krishna-pp8wz\u00a0Father land mar gayo..... motherland vidwah hogayi\n\n#Andbakht Yateem hogaye\ud83e\udd23\ud83d\ude01\ud83e\udd23\ud83d\ude04\ud83d\ude04\ud83d\ude04\ud83e\udd23\ud83d\ude01\ud83d\ude01\ud83d\ude01", "is_toxic": false, "lang": "en", "sentiment": "0", "timestamp": null, "toxicity_score": 0, "votes": 3}, {"comment": "\u200b\u00a0@Krishna-pp8wz\u00a0\ud83d\ude02\ud83d\ude02 Pakistan fighting for their country Atleast what BJP doing internal terrerism promoting Manipoor killed 1000+ people sarr\ud83d\ude02", "is_toxic": false, "lang": "en", "sentiment": "-1", "timestamp": null, "toxicity_score": 0, "votes": 0}, {"comment": "bhaii bus kar Pakh gaya ab yah comment dekhte dekhte\nsome persons are replying my comment with \"Tu jal Raha Hai\"\nMy Message to them \ud83d\udde3\ufe0f\nStop reaching. I'm not burning because of the message I\u2019m a big supporter of Iran. I\u2019m just bored of this dude's lack of originality. He\u2019s been spamming this line since video one. Support doesn't mean you have to be a bot.", "is_toxic": false, "lang": "en", "sentiment": "-1", "timestamp": null, "toxicity_score": 0, "votes": 4}, {"comment": "\u200b\u00a0@TheLastOver-2ui\u00a0\ud83d\ude02kyu nahi ho rahi padai", "is_toxic": false, "lang": "id", "sentiment": "0", "timestamp": null, "toxicity_score": 0, "votes": 3}, {"comment": "\u200b\u00a0@TheLastOver-2ui\u00a0seeda bolo na me jal raha hoon \ud83d\ude01", "is_toxic": false, "lang": "et", "sentiment": "0", "timestamp": null, "toxicity_score": 0, "votes": 2}, {"comment": "@TheLastOver-2ui\u00a0 koi to jal raha h \ud83e\udd23\ud83e\udd0c", "is_toxic": false, "lang": "fi", "sentiment": "0", "timestamp": null, "toxicity_score": 0, "votes": 2}, {"comment": "Exactly", "is_toxic": false, "lang": "unknown", "sentiment": "1", "timestamp": null, "toxicity_score": 0, "votes": 2}, {"comment": "Of course yes.", "is_toxic": false, "lang": "unknown", "sentiment": "0", "timestamp": null, "toxicity_score": 0, "votes": 2}, {"comment": "https://youtu.be/dTsNdD5QPz4?si=bw-8HJs-v8444QkX part 1\ud83c\udf89\ud83c\udf89", "is_toxic": false, "lang": "fr", "sentiment": "0", "timestamp": null, "toxicity_score": 0, "votes": 1}, {"comment": "Spanmer \ud83e\udd21", "is_toxic": false, "lang": "unknown", "sentiment": "0", "timestamp": null, "toxicity_score": 0, "votes": 0}, {"comment": "thanx brother for standing with truth", "is_toxic": false, "lang": "en", "sentiment": "0", "timestamp": null, "toxicity_score": 0, "votes": 0}, {"comment": "Abhi aur aane wale hai wait and watch modi hai toh Mumkin hai \ud83d\ude02", "is_toxic": false, "lang": "sw", "sentiment": "0", "timestamp": null, "toxicity_score": 0, "votes": 25}, {"comment": "@gsm-f4r\u00a0 election katam hone do fir dekna price to.", "is_toxic": false, "lang": "en", "sentiment": "0", "timestamp": null, "toxicity_score": 0, "votes": 8}, {"comment": "Godi media = Topi media \ud83d\ude02\ud83c\udf89", "is_toxic": false, "lang": "it", "sentiment": "0", "timestamp": null, "toxicity_score": 0, "votes": 9}, {"comment": "\ud83d\ude22", "is_toxic": false, "lang": "unknown", "sentiment": "0", "timestamp": null, "toxicity_score": 0, "votes": 5}, {"comment": "We in Kolkata are buying in proper price", "is_toxic": false, "lang": "en", "sentiment": "0", "timestamp": null, "toxicity_score": 0, "votes": 4}, {"comment": "Ab war ho gya to isme Modiji kya karenge??", "is_toxic": false, "lang": "sw", "sentiment": "0", "timestamp": null, "toxicity_score": 0, "votes": 2}, {"comment": "\u200b\u00a0@sodidyougetit7040\u00a0modi ji ne hmari foreign policy ka satyanaash kr diya hai", "is_toxic": false, "lang": "id", "sentiment": "-1", "timestamp": null, "toxicity_score": 0, "votes": 4}, {"comment": "\u200b\u00a0@sodidyougetit7040\u00a0 Nache unke samne aur war rukwaye", "is_toxic": false, "lang": "de", "sentiment": "0", "timestamp": null, "toxicity_score": 0, "votes": 2}, {"comment": "\u200b\u00a0@sodidyougetit7040\u00a0 even if our PM condemn this genocide war  it will impossible for America to do such war,we are 1.4 billion people country \ud83d\ude42", "is_toxic": false, "lang": "en", "sentiment": "-1", "timestamp": null, "toxicity_score": 0, "votes": 0}, {"comment": "yaha to sasta hai yar bhoopal me", "is_toxic": false, "lang": "id", "sentiment": "0", "timestamp": null, "toxicity_score": 0, "votes": 2}, {"comment": "@Tanay2364\u00a0 i got my cylinder for 935 rs today at my flat and delivered it today how is it possible ?", "is_toxic": false, "lang": "en", "sentiment": "-1", "timestamp": null, "toxicity_score": 0, "votes": 2}, {"comment": "\u200b\u00a0@sidhantjain9590\u00a0That was from Black market..", "is_toxic": false, "lang": "en", "sentiment": "-1", "timestamp": null, "toxicity_score": 0, "votes": 0}, {"comment": "I bought at 940\ud83d\ude05", "is_toxic": false, "lang": "en", "sentiment": "0", "timestamp": null, "toxicity_score": 0, "votes": 2}, {"comment": "Israel Father land hamara baap. India motherland", "is_toxic": false, "lang": "en", "sentiment": "0", "timestamp": null, "toxicity_score": 0, "votes": 1}, {"comment": "Tum ne black me kharida hoga \ud83d\ude02", "is_toxic": false, "lang": "sv", "sentiment": "-1", "timestamp": null, "toxicity_score": 0, "votes": 1}, {"comment": "Hamare yha to mil jaa rha bro", "is_toxic": false, "lang": "so", "sentiment": "0", "timestamp": null, "toxicity_score": 0, "votes": 1}, {"comment": "bro i get in 5 days after at 960 in faridabad", "is_toxic": false, "lang": "da", "sentiment": "0", "timestamp": null, "toxicity_score": 0, "votes": 1}, {"comment": "Ghar pe Bijli nahi hai, kiya,, Induction kharid lo, ya electric heater.. Hot plate bhi le sakte ho...!", "is_toxic": false, "lang": "en", "sentiment": "1", "timestamp": null, "toxicity_score": 0, "votes": 0}, {"comment": "Mazaa aa gaya \ud83d\ude02", "is_toxic": false, "lang": "so", "sentiment": "0", "timestamp": null, "toxicity_score": 0, "votes": 0}, {"comment": "Modiji jahan bhi jate hain, ye unka Common dialogue hai..... XXXX se  mera purana nata raha hai... Yuba abastha mein main yahan chai  bechta tha....!\ud83d\ude04", "is_toxic": false, "lang": "id", "sentiment": "-1", "timestamp": null, "toxicity_score": 0, "votes": 0}, {"comment": "Nice yaar I have paid 4500/-", "is_toxic": false, "lang": "en", "sentiment": "1", "timestamp": null, "toxicity_score": 0, "votes": 0}, {"comment": "Bhai hame toh hajar  kaa mil gya tha.. in Chhattisgarh..!! Yaa toh aapka kishmat kharab hai yaa phir aap kaha se liye aap jaano \ud83d\ude02 !!", "is_toxic": false, "lang": "so", "sentiment": "0", "timestamp": null, "toxicity_score": 0, "votes": 0}, {"comment": "Ab Godi media sirf aur surf Hindu Muslims hatred promote karega, Modi full exposed ho gsya, performance = 0/0 and sirf jhoota propaganda. Pakistan poora region ka dada bun gsya ........ Godi media = \ud83e\udd21\ud83d\udca9\ud83d\udc80", "is_toxic": false, "lang": "en", "sentiment": "1", "timestamp": null, "toxicity_score": 0, "votes": 0}, {"comment": "Andhbhakts exits all over the world, no matter how educated a country is.", "is_toxic": false, "lang": "en", "sentiment": "0", "timestamp": null, "toxicity_score": 0, "votes": 38}, {"comment": "Same logic apply to us btw\ud83d\ude05\ud83d\ude22", "is_toxic": false, "lang": "en", "sentiment": "0", "timestamp": null, "toxicity_score": 0, "votes": 32}, {"comment": "Are people of india that fool they chose modi as a prime minister \ud83d\ude02", "is_toxic": false, "lang": "en", "sentiment": "0", "timestamp": null, "toxicity_score": 0, "votes": 14}, {"comment": "\u200b\u00a0@bhatakash5083\u00a0they are", "is_toxic": false, "lang": "en", "sentiment": "0", "timestamp": null, "toxicity_score": 0, "votes": 4}, {"comment": "Dollar is climbing still", "is_toxic": false, "lang": "en", "sentiment": "0", "timestamp": null, "toxicity_score": 0, "votes": 4}, {"comment": "Yes. At least one third of them", "is_toxic": false, "lang": "en", "sentiment": "-1", "timestamp": null, "toxicity_score": 0, "votes": 1}, {"comment": "@Animesh-j5g\u00a0 what about ppl of india ???\nWoh bhi 3 vaar lol", "is_toxic": false, "lang": "en", "sentiment": "1", "timestamp": null, "toxicity_score": 0, "votes": 1}, {"comment": "They are the same as us indians", "is_toxic": false, "lang": "en", "sentiment": "0", "timestamp": null, "toxicity_score": 0, "votes": 1}, {"comment": "Aren't we ?? \ud83d\ude02", "is_toxic": false, "lang": "unknown", "sentiment": "0", "timestamp": null, "toxicity_score": 0, "votes": 0}, {"comment": "Kue ki inke ghr mai koi missile nhi girti", "is_toxic": false, "lang": "fi", "sentiment": "0", "timestamp": null, "toxicity_score": 0, "votes": 0}, {"comment": "Yeah", "is_toxic": false, "lang": "unknown", "sentiment": "0", "timestamp": null, "toxicity_score": 0, "votes": 0}, {"comment": "Sahi mai", "is_toxic": false, "lang": "unknown", "sentiment": "0", "timestamp": null, "toxicity_score": 0, "votes": 0}, {"comment": "-", "is_toxic": false, "lang": "unknown", "sentiment": "0", "timestamp": null, "toxicity_score": 0, "votes": 0}, {"comment": "Opponent bhi kamla harris hi thi bhai aur Joe Biden ka last term kuch khaas nhi tha isliye majburi mai isko chunna pada", "is_toxic": false, "lang": "id", "sentiment": "0", "timestamp": null, "toxicity_score": 0, "votes": 0}, {"comment": "yes they are", "is_toxic": false, "lang": "unknown", "sentiment": "0", "timestamp": null, "toxicity_score": 0, "votes": 0}, {"comment": "Yes, they are that stupid", "is_toxic": false, "lang": "en", "sentiment": "-1", "timestamp": null, "toxicity_score": 2, "votes": 0}, {"comment": "hijacked democracy , aipac gives money for democrats and republicans . so a win-win situation for Israeli  warlords.", "is_toxic": false, "lang": "en", "sentiment": "0", "timestamp": null, "toxicity_score": 0, "votes": 0}, {"comment": "Yes they Are !", "is_toxic": false, "lang": "unknown", "sentiment": "0", "timestamp": null, "toxicity_score": 0, "votes": 0}, {"comment": "Don't go that far, you should look here \ud83d\ude02", "is_toxic": false, "lang": "en", "sentiment": "1", "timestamp": null, "toxicity_score": 0, "votes": 0}, {"comment": "Shyam Mira Singh", "is_toxic": false, "lang": "id", "sentiment": "0", "timestamp": null, "toxicity_score": 0, "votes": 8}, {"comment": "\u200b\u00a0@captain_og1\u00a0 Yes bro \u2764", "is_toxic": false, "lang": "en", "sentiment": "0", "timestamp": null, "toxicity_score": 0, "votes": 1}, {"comment": "And Raza graphy", "is_toxic": false, "lang": "hr", "sentiment": "0", "timestamp": null, "toxicity_score": 0, "votes": 4}, {"comment": "\u200b@KukuRana-f8q Yes!!", "is_toxic": false, "lang": "so", "sentiment": "0", "timestamp": null, "toxicity_score": 0, "votes": 2}, {"comment": "\u2764\u2764\u2764", "is_toxic": false, "lang": "unknown", "sentiment": "0", "timestamp": null, "toxicity_score": 0, "votes": 2}, {"comment": "Ashok kumar pandey from the credible news too \u2764\ufe0f", "is_toxic": false, "lang": "en", "sentiment": "1", "timestamp": null, "toxicity_score": 0, "votes": 2}, {"comment": "And Kay rated", "is_toxic": false, "lang": "unknown", "sentiment": "0", "timestamp": null, "toxicity_score": 0, "votes": 1}, {"comment": "Kay rated ek hain", "is_toxic": false, "lang": "en", "sentiment": "0", "timestamp": null, "toxicity_score": 0, "votes": 0}, {"comment": "Yeah \ud83e\udee1", "is_toxic": false, "lang": "unknown", "sentiment": "0", "timestamp": null, "toxicity_score": 0, "votes": 4}, {"comment": "https://youtu.be/dTsNdD5QPz4?si=qAz2drCv_RQKsv4J part 1\ud83c\udf89\ud83c\udf89", "is_toxic": false, "lang": "fr", "sentiment": "0", "timestamp": null, "toxicity_score": 0, "votes": 0}, {"comment": "https://youtu.be/dTsNdD5QPz4?si=bw-8HJs-v8444QkX part 2\ud83c\udf89\ud83c\udf89", "is_toxic": false, "lang": "fr", "sentiment": "0", "timestamp": null, "toxicity_score": 0, "votes": 1}, {"comment": "Sure  !!ll Congrats IRAN  !ll", "is_toxic": false, "lang": "ca", "sentiment": "1", "timestamp": null, "toxicity_score": 0, "votes": 0}, {"comment": "\ud83d\ude02 Pakistan bombed Afghanistan killed 400 muslims but sarrr ummah sarrrrr", "is_toxic": false, "lang": "sv", "sentiment": "-1", "timestamp": null, "toxicity_score": 0, "votes": 0}, {"comment": "Ummah : paijannnn ye kya ho gaya sab khud me hi lar rahe hai\ud83d\ude2d\ud83d\ude2d\ud83e\udd23", "is_toxic": false, "lang": "so", "sentiment": "0", "timestamp": null, "toxicity_score": 0, "votes": 0}, {"comment": "Iran has the right to defend itself from foreign aggressors", "is_toxic": false, "lang": "en", "sentiment": "1", "timestamp": null, "toxicity_score": 0, "votes": 45}, {"comment": "\"America mein 50 saal baadh ...agar waha log padhai tab bhi karenge...\"\n.... true burnol moment\ud83d\ude02", "is_toxic": false, "lang": "id", "sentiment": "1", "timestamp": null, "toxicity_score": 0, "votes": 22}, {"comment": "Batman & Joker \u274c\nJoker and War criminal Joker \ud83e\udd21", "is_toxic": false, "lang": "en", "sentiment": "-1", "timestamp": null, "toxicity_score": 0, "votes": 12}, {"comment": "Iran be like hame maut utni hi aziz hai jitni tumhe zindagi\u2764\u2764\u2764\u2764", "is_toxic": false, "lang": "sw", "sentiment": "0", "timestamp": null, "toxicity_score": 0, "votes": 14}, {"comment": "Us : Sir badi nuksan Kar Diya iran\ud83d\ude02\ud83d\ude02", "is_toxic": false, "lang": "id", "sentiment": "0", "timestamp": null, "toxicity_score": 0, "votes": 23}, {"comment": "Real humanists support iran \u2764. Justice for Iranian girls", "is_toxic": false, "lang": "en", "sentiment": "1", "timestamp": null, "toxicity_score": 0, "votes": 18}, {"comment": "Informational video \u274c\nRoast video \u2705", "is_toxic": false, "lang": "it", "sentiment": "0", "timestamp": null, "toxicity_score": 0, "votes": 8}, {"comment": "Iran isn\u2019t going to be fooled again by these clowns.", "is_toxic": false, "lang": "en", "sentiment": "0", "timestamp": null, "toxicity_score": 0, "votes": 7}, {"comment": "These are the kind of people who bring upon destruction and despair in the world.", "is_toxic": false, "lang": "en", "sentiment": "1", "timestamp": null, "toxicity_score": 0, "votes": 9}, {"comment": "Iran has right to defend itself.", "is_toxic": false, "lang": "en", "sentiment": "1", "timestamp": null, "toxicity_score": 0, "votes": 13}, {"comment": "Akash Banerjee Respect button \u2705", "is_toxic": false, "lang": "en", "sentiment": "0", "timestamp": null, "toxicity_score": 0, "votes": 8}, {"comment": "Make America Think Again", "is_toxic": false, "lang": "id", "sentiment": "0", "timestamp": null, "toxicity_score": 0, "votes": 4}, {"comment": "Hey Akash, can we at least have a partial pivot to domestic issues, the govt is also being smart and seeking in a lot of problematic issues like the trans bill in the circumstances which this war has created without much of a debate or even awareness among the general public, this is a life changing and world order changing event yes 100% I agree with you, but we can't let the clowns who run this war divert our attention from the issues at home !\nThanks for all your detailed coverage over the past month ! Keep up the good work !", "is_toxic": false, "lang": "en", "sentiment": "1", "timestamp": null, "toxicity_score": 0, "votes": 52}, {"comment": "Not only this Dolund but also every other country's president seems to be clown these days...A single delusional asshole is determining the faith of entire world\ud83d\ude22", "is_toxic": false, "lang": "en", "sentiment": "-1", "timestamp": null, "toxicity_score": 0, "votes": 11}, {"comment": "Andhbhakt: ye nahi ho sakta sach mujhse bardast nhi hota \ud83d\ude2d\ud83e\udd23\ud83e\udd23", "is_toxic": false, "lang": "sw", "sentiment": "0", "timestamp": null, "toxicity_score": 0, "votes": 14}, {"comment": "Trump got mad\ud83d\ude02", "is_toxic": false, "lang": "unknown", "sentiment": "-1", "timestamp": null, "toxicity_score": 0, "votes": 11}, {"comment": "Absolutely Iran on Right \ud83c\uddee\ud83c\uddf7", "is_toxic": false, "lang": "en", "sentiment": "1", "timestamp": null, "toxicity_score": 0, "votes": 16}, {"comment": "America online =\ud83e\udd81\ud83e\udd81\n\n\n America offline  =\ud83e\udd21\ud83e\udd21", "is_toxic": false, "lang": "en", "sentiment": "0", "timestamp": null, "toxicity_score": 0, "votes": 12}, {"comment": "Day By Day Donald Trump Funny hote ja raha Hai \ud83d\ude02\ud83d\ude02\ud83d\ude02\ud83d\ude02\ud83d\ude02\ud83d\ude02\ud83d\ude02", "is_toxic": false, "lang": "id", "sentiment": "1", "timestamp": null, "toxicity_score": 0, "votes": 5}, {"comment": "Waiting for 3 days", "is_toxic": false, "lang": "en", "sentiment": "0", "timestamp": null, "toxicity_score": 0, "votes": 28}, {"comment": "Phir 80 million logo ko bolo kud jane nadi me \ud83d\ude02", "is_toxic": false, "lang": "sl", "sentiment": "0", "timestamp": null, "toxicity_score": 0, "votes": 1}, {"comment": "\u200b\u00a0@Krishna-pp8wz\u00a0Bina logic ki baat Kar Raha hai koi Sense hai Teri baat ka\ud83d\ude02\ud83d\ude02\ud83d\ude02\ud83d\ude02\ud83d\ude02\ud83d\ude02", "is_toxic": false, "lang": "id", "sentiment": "0", "timestamp": null, "toxicity_score": 0, "votes": 1}, {"comment": "Low iq?", "is_toxic": false, "lang": "unknown", "sentiment": "0", "timestamp": null, "toxicity_score": 0, "votes": 0}, {"comment": "\u200b\u00a0@bhattiig2\u00a0\u092b\u093f\u0930 \u0921\u0949\u0915\u094d\u091f\u0930  \u0915\u094b \u0926\u093f\u0916\u093e \u0964\n\u0932\u094b\u0917\u094b \u0915\u094b \u0915\u094d\u092f\u0942 \u092c\u0924\u093e \u0930\u0939\u093e \u0939\u0948 \u092c\u093e\u0930 \u092c\u093e\u0930", "is_toxic": false, "lang": "hi", "sentiment": "0", "timestamp": null, "toxicity_score": 0, "votes": 1}, {"comment": "Yes...! Its been over month since Aakash covered domestic news last time... maybe he is just riding on the surge and hype but whatever, so much has happened in our country since then... it will be nice to see him back in usual satire and domestic political commentary.... as this war is now in more of a stalemate situation...", "is_toxic": false, "lang": "en", "sentiment": "1", "timestamp": null, "toxicity_score": 0, "votes": 1}, {"comment": "Government is doing right thing, what is problem", "is_toxic": false, "lang": "en", "sentiment": "1", "timestamp": null, "toxicity_score": 0, "votes": 0}, {"comment": "Exactly", "is_toxic": false, "lang": "unknown", "sentiment": "1", "timestamp": null, "toxicity_score": 0, "votes": 1}, {"comment": "\ud83d\ude02 Pakistan bombed Afghanistan killed 400 muslims but sarrr ummah sarrrrr", "is_toxic": false, "lang": "id", "sentiment": "-1", "timestamp": null, "toxicity_score": 0, "votes": 2}, {"comment": "Ummah : ye kya ho gaya paijannmn\ud83e\udd23\ud83e\udd23\ud83e\udd23", "is_toxic": false, "lang": "sw", "sentiment": "0", "timestamp": null, "toxicity_score": 0, "votes": 1}, {"comment": "Allah : sare ummah wale khud hi lar rahe hai face reveal bad me hoga\ud83e\udd23\ud83e\udd23", "is_toxic": false, "lang": "so", "sentiment": "-1", "timestamp": null, "toxicity_score": 0, "votes": 1}, {"comment": "Big change... andhbakhto ki Patti pari hai sili ni ja ri \ud83d\ude02\ud83d\ude02", "is_toxic": false, "lang": "id", "sentiment": "0", "timestamp": null, "toxicity_score": 0, "votes": 2}, {"comment": "\u0907\u0928\u0936\u093e \u0905\u0932\u094d\u0932\u093e \u2764", "is_toxic": false, "lang": "unknown", "sentiment": "0", "timestamp": null, "toxicity_score": 0, "votes": 0}, {"comment": "Me too", "is_toxic": false, "lang": "unknown", "sentiment": "0", "timestamp": null, "toxicity_score": 0, "votes": 0}, {"comment": "2:54  .. literally she is smiling.. . What kind of people they are", "is_toxic": false, "lang": "en", "sentiment": "1", "timestamp": null, "toxicity_score": 0, "votes": 4}, {"comment": "IDF in bunker permanently\ud83d\ude02\ud83d\ude02 more punish Iran", "is_toxic": false, "lang": "en", "sentiment": "0", "timestamp": null, "toxicity_score": 0, "votes": 25}, {"comment": "one shot of dancing narendar Bongi,,,,,,,,,,", "is_toxic": false, "lang": "en", "sentiment": "0", "timestamp": null, "toxicity_score": 0, "votes": 9}, {"comment": "Akash do an interview with Mehdi Hasan on the Israel-Iran war. He is also an independent journalist like you and has a good knowledge of the Israel-Palestine conflict.", "is_toxic": false, "lang": "en", "sentiment": "1", "timestamp": null, "toxicity_score": 0, "votes": 16}, {"comment": "I have been watching since the war started, and every time your videos provide a lot of information. You and your team put in so much effort, and it\u2019s very difficult to post every 2\u20133 days with such detailed content. You deserve to be appreciated.", "is_toxic": false, "lang": "en", "sentiment": "1", "timestamp": null, "toxicity_score": 0, "votes": 5}, {"comment": "109 countries cannot be wrong", "is_toxic": false, "lang": "en", "sentiment": "-1", "timestamp": null, "toxicity_score": 0, "votes": 4}, {"comment": "I am Pakistani but love you", "is_toxic": false, "lang": "id", "sentiment": "1", "timestamp": null, "toxicity_score": 0, "votes": 10}, {"comment": "Sir we Bangladeshi's will never forget how you supported us. Saluted stay blessed", "is_toxic": false, "lang": "en", "sentiment": "0", "timestamp": null, "toxicity_score": 0, "votes": 5}, {"comment": "Pete Hegsett should hire Modiji ke fotugraphers \ud83d\ude02\ud83d\ude02\ud83d\ude02", "is_toxic": false, "lang": "en", "sentiment": "0", "timestamp": null, "toxicity_score": 0, "votes": 1}, {"comment": "FREE PALESTINE \ud83c\uddf5\ud83c\uddf8", "is_toxic": false, "lang": "vi", "sentiment": "1", "timestamp": null, "toxicity_score": 0, "votes": 12}, {"comment": "Sir when you said Nobody cares about people and children dying. I feel so overwhelming sadness in my heart, snd you're right no ones cares about it. \n\ud83d\ude2d", "is_toxic": false, "lang": "en", "sentiment": "1", "timestamp": null, "toxicity_score": 0, "votes": 1}, {"comment": "The only thing necessary for the triumph of evil is for good men to do nothing.", "is_toxic": false, "lang": "en", "sentiment": "1", "timestamp": null, "toxicity_score": 0, "votes": 3}, {"comment": "The level of frustration has touched new heights for Akash Bro, Salute to you brother \ud83c\udf89\ud83c\udf89", "is_toxic": false, "lang": "en", "sentiment": "1", "timestamp": null, "toxicity_score": 0, "votes": 1}, {"comment": "Maza aagaya America paw paw\ud83d\ude02\ud83d\ude02\ud83d\ude02\ud83d\ude02", "is_toxic": false, "lang": "tl", "sentiment": "0", "timestamp": null, "toxicity_score": 0, "votes": 3}, {"comment": "Americans have elected a joker and getting to see circus free of cost, each day, every day, over and over.....", "is_toxic": false, "lang": "en", "sentiment": "1", "timestamp": null, "toxicity_score": 0, "votes": 2}, {"comment": "Any Bangladeshi \ud83c\udde7\ud83c\udde9\ud83c\udde7\ud83c\udde9\ud83c\udde7\ud83c\udde9??", "is_toxic": false, "lang": "tl", "sentiment": "0", "timestamp": null, "toxicity_score": 0, "votes": 4}, {"comment": "\u0908\u0930\u093e\u0928 \u0915\u094b \u0907\u091c\u0930\u093e\u0907\u0932 \u0915\u094b \u092a\u0942\u0930\u0940 \u0924\u0930\u0939 \u0938\u0947 \u0928\u0937\u094d\u091f \u0915\u0930 \u0926\u0947\u0928\u093e \u091a\u093e\u0939\u093f\u090f\u0964\n\u0926\u0941\u0928\u093f\u092f\u093e\u0902 \u0915\u093e 70% \u0939\u093f\u0938\u094d\u0938\u093e \u0908\u0930\u093e\u0928 \u0915\u0947 \u092a\u0915\u094d\u0937 \u092e\u0947 \u0939\u0948\u0964 \u092c\u0939\u093e\u0926\u0941\u0930 \u0908\u0930\u093e\u0928 \u0915\u094b \u0938\u0932\u093e\u092e!\ud83d\udcaa\ud83d\udd25", "is_toxic": false, "lang": "hi", "sentiment": "0", "timestamp": null, "toxicity_score": 0, "votes": 11}, {"comment": "US making sure every country rethinks about having nukes....", "is_toxic": false, "lang": "en", "sentiment": "1", "timestamp": null, "toxicity_score": 0, "votes": 6}, {"comment": "Before- No more wars!\nNow- No, more wars!", "is_toxic": false, "lang": "en", "sentiment": "0", "timestamp": null, "toxicity_score": 0, "votes": 1}, {"comment": "Thank you Banerjee for exposing the Epstien Regime.", "is_toxic": false, "lang": "en", "sentiment": "0", "timestamp": null, "toxicity_score": 0, "votes": 7}, {"comment": "Main character syndrome \ud83e\udd21", "is_toxic": false, "lang": "en", "sentiment": "1", "timestamp": null, "toxicity_score": 0, "votes": 0}, {"comment": "\ud83d\ude02 Pakistan bombed Afghanistan killed 400 muslims but sarrr ummah sarrrrr", "is_toxic": false, "lang": "id", "sentiment": "-1", "timestamp": null, "toxicity_score": 0, "votes": 0}, {"comment": "\u200b\u00a0@Krishna-pp8wz\u00a0are Pakistan Afghanistan bare main kyon La raha hai  batana aukat nahin kuchh logical baat karne ki\ud83d\ude02\ud83d\ude02\ud83d\ude02\ud83d\ude02", "is_toxic": false, "lang": "id", "sentiment": "1", "timestamp": null, "toxicity_score": 0, "votes": 1}, {"comment": "Mat kar lala , IT cell ajayga !", "is_toxic": false, "lang": "so", "sentiment": "0", "timestamp": null, "toxicity_score": 0, "votes": 0}, {"comment": "He is idiot on issues that are serious", "is_toxic": false, "lang": "en", "sentiment": "-1", "timestamp": null, "toxicity_score": 4, "votes": 0}, {"comment": "\u200b\u00a0@Infinitelife-d7v\u00a0 yes you are right he is idiot for Andbhakts", "is_toxic": false, "lang": "en", "sentiment": "-1", "timestamp": null, "toxicity_score": 4, "votes": 2}, {"comment": "\ud83d\ude02\ud83d\ude02", "is_toxic": false, "lang": "unknown", "sentiment": "0", "timestamp": null, "toxicity_score": 0, "votes": 0}, {"comment": "\ud83d\ude02\ud83d\ude02\ud83d\ude02 kanglus", "is_toxic": false, "lang": "unknown", "sentiment": "0", "timestamp": null, "toxicity_score": 0, "votes": 0}, {"comment": "Trump is become blind in Power!!", "is_toxic": false, "lang": "en", "sentiment": "-1", "timestamp": null, "toxicity_score": 0, "votes": 0}, {"comment": "\ud83d\udc9a\ud83c\udde7\ud83c\udde9\ud83c\uddee\ud83c\uddf7", "is_toxic": false, "lang": "unknown", "sentiment": "0", "timestamp": null, "toxicity_score": 0, "votes": 0}, {"comment": "When Thedeshbhakt touch a topic with truth and democracy it\u2019s always win. Love from Bangladesh \ud83c\udde7\ud83c\udde9 \u2764", "is_toxic": false, "lang": "en", "sentiment": "1", "timestamp": null, "toxicity_score": 0, "votes": 0}, {"comment": "Deaths are all around but humanity is long goon", "is_toxic": false, "lang": "en", "sentiment": "-1", "timestamp": null, "toxicity_score": 0, "votes": 1}, {"comment": "I am Truly saying...\nMaine Desh ko bevkoof nahi banaya hai balki \nBevkoof logon ne mujhe PM banaya hai.\n\ud83d\ude02\ud83d\ude02", "is_toxic": false, "lang": "sw", "sentiment": "0", "timestamp": null, "toxicity_score": 0, "votes": 3}, {"comment": "America ko iran se kamzor krwane ke baad china apna khel shuru krne wala h taiwan me \ud83d\ude02", "is_toxic": false, "lang": "sw", "sentiment": "0", "timestamp": null, "toxicity_score": 0, "votes": 1}, {"comment": "Respected Sir,\n\nI am a UPSC aspirant and a regular follower of your channel, The Deshbhakt. Your content has significantly enhanced my understanding of global politics and current affairs. I engage with your videos with great focus and consistently find them insightful and intellectually enriching.\n\nI would like to request you to consider creating a dedicated video for UPSC aspirants, where you could share your preparation strategy, approach, and guidance. Given that you have yourself been a UPSC aspirant, your perspective would be immensely valuable for students like me.\n\nThank you for your time and for the impactful content you create.", "is_toxic": false, "lang": "en", "sentiment": "1", "timestamp": null, "toxicity_score": 0, "votes": 2}, {"comment": "I think Akash need to also do an analysis on how Trump accumulated his wealth...I don't think he is a good negotiator and his dad built all the fortune", "is_toxic": false, "lang": "en", "sentiment": "1", "timestamp": null, "toxicity_score": 0, "votes": 8}, {"comment": "Trump ne America ke so called image ki Maa Bahen ker di hai\ud83d\ude05", "is_toxic": false, "lang": "id", "sentiment": "0", "timestamp": null, "toxicity_score": 0, "votes": 1}, {"comment": "First view from Bengal \u2764\u2764", "is_toxic": false, "lang": "en", "sentiment": "1", "timestamp": null, "toxicity_score": 0, "votes": 4}, {"comment": "Anyone watching from Superpower Bangladesh\ud83c\udde7\ud83c\udde9", "is_toxic": false, "lang": "en", "sentiment": "0", "timestamp": null, "toxicity_score": 0, "votes": 3}, {"comment": "What did US think\u2014that by going into Iran, assassinating their head of state and other top officials, bombing schools where small children study, striking hospitals, destroying energy sources, and bombing civilian buildings killing many people, Iran would simply retaliate a little\u2014bomb a few of your mango and coconut trees\u2014and then feel satisfied and walk away?", "is_toxic": false, "lang": "en", "sentiment": "1", "timestamp": null, "toxicity_score": 0, "votes": 2}, {"comment": "Donald Trump \u274c\ufe0f\nPetrol pump \u2705\ufe0f\nvenezuela \u274c\ufe0f\nThis is iran \u2705\ufe0f", "is_toxic": false, "lang": "en", "sentiment": "0", "timestamp": null, "toxicity_score": 0, "votes": 4}, {"comment": "Mr Donald drunk \ud83d\ude02\ud83d\ude02", "is_toxic": false, "lang": "da", "sentiment": "0", "timestamp": null, "toxicity_score": 0, "votes": 2}, {"comment": "Self Talk Is Best For \"Mental Health\" \ud83d\ude01\ud83d\ude01\u270c\ufe0f", "is_toxic": false, "lang": "en", "sentiment": "1", "timestamp": null, "toxicity_score": 0, "votes": 1}, {"comment": "Waiting from 3 days", "is_toxic": false, "lang": "en", "sentiment": "0", "timestamp": null, "toxicity_score": 0, "votes": 4}, {"comment": "Golmaal hai bhai sab golmaal hai\ud83d\ude02", "is_toxic": false, "lang": "so", "sentiment": "0", "timestamp": null, "toxicity_score": 0, "votes": 1}, {"comment": "No one milked this war like you bro\ud83d\ude02\ud83d\ude02\ud83d\ude02\ud83d\ude02\ud83d\ude02 congo thode dedo mujhe bhi pese \ud83d\ude02\ud83d\ude02\ud83d\ude02\ud83d\ude02", "is_toxic": false, "lang": "en", "sentiment": "0", "timestamp": null, "toxicity_score": 0, "votes": 4}, {"comment": "Deshbhakt income become 10x", "is_toxic": false, "lang": "en", "sentiment": "0", "timestamp": null, "toxicity_score": 0, "votes": 2}, {"comment": "US GAYA", "is_toxic": false, "lang": "unknown", "sentiment": "0", "timestamp": null, "toxicity_score": 0, "votes": 4}, {"comment": "I hope you remain on the right side of history, always!", "is_toxic": false, "lang": "en", "sentiment": "1", "timestamp": null, "toxicity_score": 0, "votes": 1}, {"comment": "Iran be like  Ladle ghop ghop ghop ghop ghop", "is_toxic": false, "lang": "af", "sentiment": "0", "timestamp": null, "toxicity_score": 0, "votes": 3}, {"comment": "In Vietnam??? Or in Taiwan?", "is_toxic": false, "lang": "de", "sentiment": "0", "timestamp": null, "toxicity_score": 0, "votes": 0}, {"comment": "\u200b\u00a0@nuzhatnizat\u00a0my mistake \ud83d\ude14 \nAmerica ki vietnam me galtiya sun sun kr wahi yad rahta h mujhe mgar America ko nhi", "is_toxic": false, "lang": "id", "sentiment": "0", "timestamp": null, "toxicity_score": 0, "votes": 0}, {"comment": "Where you from  in Bengal  ??", "is_toxic": false, "lang": "en", "sentiment": "0", "timestamp": null, "toxicity_score": 0, "votes": 0}, {"comment": "Woooooooooooo sir thenx for the deep informeted video and I am soooooooooo excited for the your next video's continue and good bless you and i am fully supported you..................\ud83d\ude2e", "is_toxic": false, "lang": "en", "sentiment": "1", "timestamp": null, "toxicity_score": 0, "votes": 1}, {"comment": "Remember that while other countries get destroyed in war...\n\nAmerica\n\n\u00a0simply loses interest.\"", "is_toxic": false, "lang": "en", "sentiment": "-1", "timestamp": null, "toxicity_score": 0, "votes": 2}, {"comment": "May God Protect Iran from evil of this era", "is_toxic": false, "lang": "en", "sentiment": "-1", "timestamp": null, "toxicity_score": 0, "votes": 1}, {"comment": "Gulf countries \u092e\u0947\u0902 \u090f\u0915 \u091c\u0940\u0924\u093e \u091c\u0917\u0924\u093e  \u0936\u0947\u0930 \u0939\u0948 \u0908\u0930\u093e\u0928 \u091c\u094b \u0905\u092e\u0947\u0930\u093f\u0915\u093e \u091c\u0948\u0938\u0947 superpower \u0915\u0947 \u0938\u093e\u092e\u0928\u0947 \u0918\u0941\u091f\u0928\u0947 \u091f\u0947\u0915\u0928\u0947 \u0938\u0947 \u0907\u0928\u0915\u093e\u0930 \u0915\u0930 \u0926\u093f\u092f\u093e\nBravo Iran \u270d\ufe0f\u270d\ufe0f", "is_toxic": false, "lang": "hi", "sentiment": "0", "timestamp": null, "toxicity_score": 0, "votes": 2}, {"comment": "Trump tried calling Iran for peace talks and then realized he was dialling on Khamenei's phone that was decimated along with him on Feb 28", "is_toxic": false, "lang": "en", "sentiment": "0", "timestamp": null, "toxicity_score": 0, "votes": 0}, {"comment": "\u0926\u0941\u0928\u093f\u092f\u093e \u092e\u0947\u0902 \u0938\u093e\u092e\u093e\u091c\u093f\u0915 \u0928\u0948\u0924\u093f\u0915\u0924\u093e \u0915\u0940 \u092e\u094c\u0924 \u0915\u093e \u0924\u092e\u093e\u0936\u093e \u091a\u0932 \u0930\u0939\u093e \u0939\u0948...\u091c\u093f\u0938\u0947 \u0938\u093f\u0930\u094d\u092b \u0938\u0930\u094d\u0915\u0938 \u0939\u0940 \u0915\u0939\u093e \u091c\u093e \u0938\u0915\u0924\u093e \u0939\u0948... \n\u0926\u0941\u0928\u093f\u092f\u093e \u0915\u0940 \u0905\u0927\u093f\u0915\u093e\u0902\u0936 \u0906\u092c\u093e\u0926\u0940...\u0935\u093f\u0936\u0947\u0937\u0915\u0930 \u0935\u0947 \u0926\u0947\u0936 \u091c\u094b \u0926\u0941\u0928\u093f\u092f\u093e \u0915\u0947 \u0915\u0908 \u090f\u0915 \u0939\u093f\u0938\u094d\u0938\u094b\u0902 \u092e\u0947\u0902 \u0916\u0941\u0932\u0947\u0906\u092e \u0939\u094b\u0924\u0940 \u0939\u093f\u0902\u0938\u093e \u0915\u0947 \u0936\u093f\u0915\u093e\u0930 \u0928\u0939\u0940\u0902 \u0939\u0941\u090f \u0939\u0948\u0902...\u0935\u0947 \u0916\u093e\u092e\u094b\u0936 \u0926\u0930\u094d\u0936\u0915 \u0930\u0939 \u0915\u0930 \u092e\u093e\u0928\u0935\u0924\u093e \u0915\u0947 \u0916\u093f\u0932\u093e\u092b \u091c\u092c\u0930\u0928 \u091b\u0947\u0921\u093c\u0940 \u0917\u0908 \u0907\u0928 \u091c\u0902\u0917\u094b\u0902 \u0915\u0947 \u0938\u0939\u092f\u094b\u0917\u0940 \u0928\u0939\u0940\u0902 \u0924\u094b \u0915\u094c\u0928 \u0939\u0948\u0902 \u2753 \n\u0905\u0917\u0930 \u0935\u0947 \u0916\u093c\u093e\u092e\u094b\u0936 \u0930\u0939 \u0915\u0930 \u0938\u092e\u091d\u0924\u0947 \u0939\u0948\u0902 \u0915\u093f \u0935\u0947 \u092c\u091a \u091c\u093e\u090f\u0902\u0917\u0947...\u0924\u094b \u0935\u0947 \u090f\u0915 \u0910\u0938\u0940 \u0916\u0941\u0936\u092b\u0939\u092e\u0940 \u092e\u0947\u0902 \u091c\u0940 \u0930\u0939\u0947 \u0939\u0948\u0902 \u091c\u094b \u091c\u094d\u092f\u093e\u0926\u093e \u0932\u0902\u092c\u0940 \u0928\u0939\u0940\u0902 \u0930\u0939\u0928\u0947 \u0935\u093e\u0932\u0940...\u0906\u0917 \u0915\u0940 \u0924\u092a\u093f\u0936 \u0906\u091c \u0928\u0939\u0940\u0902 \u0924\u094b \u0915\u0932 \u0926\u0941\u0928\u093f\u092f\u093e \u092d\u0930 \u092e\u0947\u0902 \u092b\u0948\u0932 \u091c\u093e\u090f \u0924\u094b \u0924\u093e\u091c\u094d\u091c\u0941\u092c \u0928\u0939\u0940\u0902 \u0939\u094b\u0928\u093e \u091a\u093e\u0939\u093f\u090f...\n\ud83d\ude4f", "is_toxic": false, "lang": "hi", "sentiment": "0", "timestamp": null, "toxicity_score": 0, "votes": 2}, {"comment": "Excellent truthful news analysis and good job \ud83d\udc4d\ud83d\udc4d\ud83d\udc4d\ud83d\udc4d\ud83d\udc4d\ud83d\udc4d\ud83d\udc4d\ud83d\udc4d\ud83d\udc4d", "is_toxic": false, "lang": "en", "sentiment": "1", "timestamp": null, "toxicity_score": 0, "votes": 1}, {"comment": "Donald Trump takes Iran lightly \ud83d\ude02", "is_toxic": false, "lang": "en", "sentiment": "0", "timestamp": null, "toxicity_score": 0, "votes": 2}, {"comment": "Thanks", "is_toxic": false, "lang": "unknown", "sentiment": "1", "timestamp": null, "toxicity_score": 0, "votes": 1}, {"comment": "Trump\u274c Petrol Pump\u2705", "is_toxic": false, "lang": "id", "sentiment": "0", "timestamp": null, "toxicity_score": 0, "votes": 2}, {"comment": "When a clown moves into a palace, he doesn't become a king. The palace becomes a circus.", "is_toxic": false, "lang": "en", "sentiment": "0", "timestamp": null, "toxicity_score": 0, "votes": 0}, {"comment": "Berozgar wale like kare\ud83d\ude02", "is_toxic": false, "lang": "af", "sentiment": "0", "timestamp": null, "toxicity_score": 0, "votes": 3}, {"comment": "Sir alot alot of love from \ud83c\uddf5\ud83c\uddf0....\u2764\u2764\u2764", "is_toxic": false, "lang": "en", "sentiment": "1", "timestamp": null, "toxicity_score": 0, "votes": 1}, {"comment": "US Bhari Badtameez\ud83d\ude02", "is_toxic": false, "lang": "de", "sentiment": "0", "timestamp": null, "toxicity_score": 0, "votes": 3}, {"comment": "Donald Trump is NOT delusional... He is doing all this so that the world will simply ignore him. He is using this war to keep to office, he is using this war to get out of NATO and attack Europe & Canada (for Greenland) and also simultaneously preparing the ground to eliminate his political opposition in-country. The guy is by no means delusional. He is a hardened career criminal and is dragging the world to hell.", "is_toxic": false, "lang": "en", "sentiment": "-1", "timestamp": null, "toxicity_score": 0, "votes": 2}, {"comment": "J in Donald J. Trump is Joker :P", "is_toxic": false, "lang": "en", "sentiment": "0", "timestamp": null, "toxicity_score": 0, "votes": 4}, {"comment": "thank you for the well informed updates, highly appreciated", "is_toxic": false, "lang": "en", "sentiment": "1", "timestamp": null, "toxicity_score": 0, "votes": 1}, {"comment": "You r so neutral, rational, u explained difficult things so easily and accurately.. Every time i see ur analysis my knowledge increasing a lot..love from \ud83c\udde7\ud83c\udde9", "is_toxic": false, "lang": "en", "sentiment": "1", "timestamp": null, "toxicity_score": 0, "votes": 1}, {"comment": "We Indians especially from Bihar and Bengals are very smart. I am also from Bengal.", "is_toxic": false, "lang": "en", "sentiment": "1", "timestamp": null, "toxicity_score": 0, "votes": 0}, {"comment": "Love you brother", "is_toxic": false, "lang": "en", "sentiment": "1", "timestamp": null, "toxicity_score": 0, "votes": 1}]}